docs/misc/z-example-config-reward.yaml
docs/misc/z-example-config-sft.yaml
docs/misc/z-example-fbopt-rl.yaml
docs/misc/z-example-gemma3-rl.yaml
docs/misc/z-example-gpt2-rl.yaml
docs/misc/z-example-rlhf-fbopt.yaml
docs/misc/z-example-rlhf-gemma.yaml
docs/misc/z-example-rlhf-test.yaml
experl/__init__.py
experl/cli.py
experl/rlhf_orchestrator.py
experl/config/__init__.py
experl/config/config_loader.py
experl/config/schema/__init__.py
experl/config/schema/config_classes.py
experl/config/yaml/config.yaml
experl/config/yaml/dpo.yaml
experl/config/yaml/ppo.yaml
experl/config/yaml/dataset/dataset.yaml
experl/config/yaml/dpo/rlhf.yaml
experl/config/yaml/dpo/dpo/dpo.yaml
experl/config/yaml/dpo/eval/eval.yaml
experl/config/yaml/dpo/sft/sft.yaml
experl/config/yaml/model/model.yaml
experl/config/yaml/ppo/rlhf.yaml
experl/config/yaml/ppo/eval/eval.yaml
experl/config/yaml/ppo/ppo/ppo.yaml
experl/config/yaml/ppo/reward/reward.yaml
experl/config/yaml/ppo/sft/sft.yaml
experl/evaluation/__init__.py
experl/evaluation/dpo_evaluator.py
experl/evaluation/evaluator.py
experl/evaluation/judge_evaluator.py
experl/evaluation/ppo_evaluator.py
experl/evaluation/reward_judge_evaluator.py
experl/logger/__init__.py
experl/logger/mlflow_logger.py
experl/models/__init__.py
experl/models/reward_model.py
experl/trainer/__init__.py
experl/trainer/base_trainer.py
experl/trainer/dpo_trainer.py
experl/trainer/ppo_trainer.py
experl/trainer/reward_model_trainer.py
experl/trainer/sft_trainer.py
experl/utils/__init__.py
experl/utils/common_utils.py
experl/utils/dataset_utils.py
experl/utils/logging_utils.py
experl/utils/process_runner.py
experl/utils/trainer_utils.py
experl_core-0.1.0.dev4.dist-info/licenses/LICENSE
experl_core-0.1.0.dev4.dist-info/METADATA
experl_core-0.1.0.dev4.dist-info/WHEEL
experl_core-0.1.0.dev4.dist-info/entry_points.txt
experl_core-0.1.0.dev4.dist-info/top_level.txt
experl_core-0.1.0.dev4.dist-info/RECORD
