Metadata-Version: 2.4
Name: experl-core
Version: 0.1.0.dev4
Summary: Train large language models using reinforcement learning with human feedback.
Home-page: https://github.com/vjkhambe/experl
Author: Vijay Khambe
Author-email: vj.khambe@gmail.com
Keywords: transformers,huggingface,language modeling,post-training,rlhf,sft,dpo,ppo
Classifier: Development Status :: 4 - Beta
Classifier: Intended Audience :: Developers
Classifier: Intended Audience :: Science/Research
Classifier: Natural Language :: English
Classifier: Operating System :: OS Independent
Classifier: Programming Language :: Python :: 3
Classifier: Programming Language :: Python :: 3.12
Classifier: Programming Language :: Python :: 3.13
Requires-Python: >=3.12
License-File: LICENSE
Requires-Dist: accelerate==1.11.0
Requires-Dist: datasets==4.3.0
Requires-Dist: transformers==4.57.1
Requires-Dist: trl==0.24.0
Requires-Dist: mlflow==3.5.1
Requires-Dist: hydra-core==1.3.2
Provides-Extra: cuda
Requires-Dist: bitsandbytes==0.48.2; extra == "cuda"
Requires-Dist: torchvision==0.24.0; extra == "cuda"
Dynamic: license-file
